interactive_models/__init__.py
interactive_models/apps.py
interactive_models/management/__init__.py
interactive_models/management/commands/__init__.py
interactive_models/management/commands/_check_models_file.py
interactive_models/management/commands/_parse_fields.py
interactive_models/management/commands/_render_model.py
interactive_models/management/commands/models.py
interactive_models/templates/model_template.py.template
django_interactive_models-0.3.0.dist-info/LICENSE
django_interactive_models-0.3.0.dist-info/METADATA
django_interactive_models-0.3.0.dist-info/WHEEL
django_interactive_models-0.3.0.dist-info/top_level.txt
django_interactive_models-0.3.0.dist-info/RECORD
