Metadata-Version: 2.1
Name: django-interactive-models
Version: 0.3.0
Summary: a CLI Tool to create django models interactively
Author-email: Ferran Jovell <ferran.jovell+gh@gmail.com>
License: MIT License
Keywords: django
Classifier: Intended Audience :: Developers
Classifier: License :: OSI Approved :: MIT License
Classifier: Programming Language :: Python :: 3.8
Classifier: Programming Language :: Python :: 3.9
Classifier: Programming Language :: Python :: 3.10
Classifier: Programming Language :: Python :: 3.11
Classifier: Operating System :: OS Independent
Classifier: Topic :: Software Development :: Libraries
Classifier: Topic :: Utilities
Classifier: Environment :: Web Environment
Classifier: Framework :: Django
Requires-Python: >=3.9
License-File: LICENSE
Requires-Dist: Django >=3.2.15
Provides-Extra: test
Requires-Dist: pytest ; extra == 'test'
Requires-Dist: pytest-cov ; extra == 'test'
Requires-Dist: pytest-django ; extra == 'test'
Requires-Dist: mypy <=0.970 ; extra == 'test'
Requires-Dist: django-stubs[compatible-mypy] ; extra == 'test'
